leap_data_management_utils/__init__.py
leap_data_management_utils/_version.py
leap_data_management_utils/bq_interfaces.py
leap_data_management_utils/catalog.py
leap_data_management_utils/cmip_catalog.py
leap_data_management_utils/cmip_testing.py
leap_data_management_utils/cmip_transforms.py
leap_data_management_utils/data_management_transforms.py
leap_data_management_utils/testing_notebooks/testing_cmip_bigquery.ipynb
leap_data_management_utils/tests/test_cmip_catalog.py
leap_data_management_utils/tests/test_cmip_transforms.py
leap_data_management_utils/tests/test_data_management_transforms.py
leap_data_management_utils-0.0.19.dist-info/licenses/LICENSE
leap_data_management_utils-0.0.19.dist-info/METADATA
leap_data_management_utils-0.0.19.dist-info/WHEEL
leap_data_management_utils-0.0.19.dist-info/entry_points.txt
leap_data_management_utils-0.0.19.dist-info/top_level.txt
leap_data_management_utils-0.0.19.dist-info/RECORD
