Metadata-Version: 2.4
Name: leap-data-management-utils
Version: 0.0.19
Summary: LEAP / pangeo-forge-recipes extension library for logging data in Google Big Query
Author-email: LEAP <leap@columbia.edu>
Classifier: Development Status :: 4 - Beta
Classifier: Intended Audience :: Science/Research
Classifier: License :: OSI Approved :: MIT License
Classifier: Operating System :: OS Independent
Classifier: Programming Language :: Python :: 3
Classifier: Programming Language :: Python :: 3.10
Classifier: Programming Language :: Python :: 3.11
Classifier: Programming Language :: Python :: 3.9
Classifier: Programming Language :: Python
Classifier: Topic :: Scientific/Engineering
Requires-Python: >=3.9
License-File: LICENSE
Requires-Dist: cftime
Requires-Dist: dask
Requires-Dist: ruamel.yaml
Requires-Dist: xarray
Requires-Dist: zarr<3
Provides-Extra: bigquery
Requires-Dist: db_dtypes; extra == "bigquery"
Requires-Dist: google-api-core; extra == "bigquery"
Requires-Dist: google-cloud-bigquery; extra == "bigquery"
Requires-Dist: pangeo-forge-esgf>0.3.0; extra == "bigquery"
Requires-Dist: tqdm; extra == "bigquery"
Provides-Extra: catalog
Requires-Dist: aiohttp; extra == "catalog"
Requires-Dist: cf_xarray; extra == "catalog"
Requires-Dist: kerchunk>=0.2.6; extra == "catalog"
Requires-Dist: pydantic-core; extra == "catalog"
Requires-Dist: pydantic>=2; extra == "catalog"
Requires-Dist: requests; extra == "catalog"
Requires-Dist: universal-pathlib; extra == "catalog"
Provides-Extra: complete
Requires-Dist: leap-data-management-utils[catalog,pangeo-forge]; extra == "complete"
Provides-Extra: dev
Requires-Dist: leap-data-management-utils[test]; extra == "dev"
Requires-Dist: pre-commit; extra == "dev"
Provides-Extra: pangeo-forge
Requires-Dist: apache-beam==2.60.0; extra == "pangeo-forge"
Requires-Dist: dynamic-chunks; extra == "pangeo-forge"
Requires-Dist: leap-data-management-utils[bigquery]; extra == "pangeo-forge"
Requires-Dist: pangeo-forge-recipes; extra == "pangeo-forge"
Provides-Extra: test
Requires-Dist: leap-data-management-utils[complete]; extra == "test"
Requires-Dist: pytest; extra == "test"
Dynamic: license-file
